{
  "titulo": "The Weeknd - Save Your Tears (Legendado | Lyrics + Tradução)",
  "artista": "The Weeknd",
  "videoId": "30gbL44vjA8",
  "timestamps": [
    {
      "startTime": 9,
      "endTime": 17,
      "text": "Ooh, yeah\nI saw you dancing in a crowded room",
      "translation": "Ooh, sim\nEu vi você dançando em uma sala cheia"
    },
    {
      "startTime": 17,
      "endTime": 25,
      "text": "You look so happy when I'm not with you",
      "translation": "Você parece tão feliz quando não estou com você"
    },
    {
      "startTime": 25,
      "endTime": 33,
      "text": "But then you saw me, caught you by surprise",
      "translation": "Mas aí você me viu, te peguei de surpresa"
    },
    {
      "startTime": 33,
      "endTime": 41,
      "text": "A single tear falling from your eye",
      "translation": "Uma única lágrima caindo do seu olho"
    },
    {
      "startTime": 41,
      "endTime": 49,
      "text": "I don't know why I run away",
      "translation": "Eu não sei por que eu fujo"
    },
    {
      "startTime": 49,
      "endTime": 57,
      "text": "I'll make you cry when I run away",
      "translation": "Eu te faço chorar quando eu fujo"
    },
    {
      "startTime": 57,
      "endTime": 64,
      "text": "Take me back 'cause I wanna stay",
      "translation": "Me leve de volta porque eu quero ficar"
    },
    {
      "startTime": 64,
      "endTime": 73,
      "text": "Save your tears for another day",
      "translation": "Guarde suas lágrimas para outro dia"
    },
    {
      "startTime": 73,
      "endTime": 81,
      "text": "Save your tears for another day",
      "translation": "Guarde suas lágrimas para outro dia"
    },
    {
      "startTime": 81,
      "endTime": 89,
      "text": "Met you once under a pisces moon",
      "translation": "Te conheci uma vez sob a lua em peixes"
    },
    {
      "startTime": 89,
      "endTime": 97,
      "text": "I kept my distance 'cause I know that you",
      "translation": "Eu mantive distância porque sei que você"
    },
    {
      "startTime": 97,
      "endTime": 104,
      "text": "Don't like when I'm with somebody else",
      "translation": "Não gosta quando estou com outra pessoa"
    },
    {
      "startTime": 104,
      "endTime": 112,
      "text": "I couldn't bring myself to hide the truth",
      "translation": "Eu não consegui me obrigar a esconder a verdade"
    },
    {
      "startTime": 112,
      "endTime": 120,
      "text": "I don't know why I run away",
      "translation": "Eu não sei por que eu fujo"
    },
    {
      "startTime": 120,
      "endTime": 127,
      "text": "I'll make you cry when I run away",
      "translation": "Eu te faço chorar quando eu fujo"
    },
    {
      "startTime": 127,
      "endTime": 135,
      "text": "Take me back 'cause I wanna stay",
      "translation": "Me leve de volta porque eu quero ficar"
    },
    {
      "startTime": 135,
      "endTime": 143,
      "text": "Save your tears for another day",
      "translation": "Guarde suas lágrimas para outro dia"
    },
    {
      "startTime": 143,
      "endTime": 152,
      "text": "I made you think that I would always stay",
      "translation": "Eu fiz você pensar que eu sempre ficaria"
    },
    {
      "startTime": 152,
      "endTime": 160,
      "text": "I said some things that I should never say",
      "translation": "Eu disse algumas coisas que eu nunca deveria dizer"
    },
    {
      "startTime": 160,
      "endTime": 168,
      "text": "Yeah, I broke your heart like someone did to mine",
      "translation": "Sim, eu quebrei seu coração como alguém fez com o meu"
    },
    {
      "startTime": 168,
      "endTime": 176,
      "text": "And now you won't love me for a second time",
      "translation": "E agora você não vai me amar por uma segunda vez"
    },
    {
      "startTime": 176,
      "endTime": 184,
      "text": "I don't know why I run away",
      "translation": "Eu não sei por que eu fujo"
    },
    {
      "startTime": 184,
      "endTime": 191,
      "text": "I'll make you cry when I run away",
      "translation": "Eu te faço chorar quando eu fujo"
    },
    {
      "startTime": 191,
      "endTime": 199,
      "text": "Save your tears for another day",
      "translation": "Guarde suas lágrimas para outro dia"
    },
    {
      "startTime": 199,
      "endTime": 207,
      "text": "Save your tears for another day",
      "translation": "Guarde suas lágrimas para outro dia"
    },
    {
      "startTime": 207,
      "endTime": 216,
      "text": "Save your tears for another day",
      "translation": "Guarde suas lágrimas para outro dia"
    }
  ]
}
